cythoncartesian2/README.MD
cythoncartesian2/__init__.py
cythoncartesian2/requirements.txt
cythoncartesian2/thirdparty.json
cythoncartesian2-0.10.dist-info/LICENSE.rst
cythoncartesian2-0.10.dist-info/METADATA
cythoncartesian2-0.10.dist-info/WHEEL
cythoncartesian2-0.10.dist-info/top_level.txt
cythoncartesian2-0.10.dist-info/RECORD
