Metadata-Version: 2.1
Name: cythoncartesian2
Version: 0.10
Summary: Cartesian Product for NumPy - 40x faster than NumPy + itertools.product
Home-page: https://github.com/hansalemaos/cythoncartesian2
Author: Johannes Fischer
Author-email: aulasparticularesdealemaosp@gmail.com
License: MIT
Keywords: cython,arrays,cartesian,numpy
Classifier: Development Status :: 4 - Beta
Classifier: Programming Language :: Python :: 3 :: Only
Classifier: Programming Language :: Python :: 3.10
Classifier: Topic :: Software Development :: Libraries :: Python Modules
Classifier: Topic :: Utilities
License-File: LICENSE.rst
Requires-Dist: Cython
Requires-Dist: numpy
